angelou/__init__.py
angelou/remove_non_word_characters.py
angelou/sparksession.py
angelou/transformations.py
angelou-0.1.0.dist-info/WHEEL
angelou-0.1.0.dist-info/METADATA
angelou-0.1.0.dist-info/RECORD
