Metadata-Version: 2.1
Name: angelou
Version: 0.1.0
Summary: 
Author: ext_jarismendi
Author-email: ext_jarismendi@bancofalabella.com.co
Requires-Python: >=3.8,<4.0
Classifier: Programming Language :: Python :: 3
Classifier: Programming Language :: Python :: 3.8
Classifier: Programming Language :: Python :: 3.9
Requires-Dist: pyspark (>=3.0.1,<4.0.0)
Requires-Dist: quinn (>=0.8.0,<0.9.0)
